mdot/__init__.py
mdot/main.py
mdot-0.1.1.dist-info/licenses/License
mdot-0.1.1.dist-info/METADATA
mdot-0.1.1.dist-info/WHEEL
mdot-0.1.1.dist-info/entry_points.txt
mdot-0.1.1.dist-info/top_level.txt
mdot-0.1.1.dist-info/RECORD
