Metadata-Version: 2.4
Name: mdot
Version: 0.1.1
Summary: A simple CLI Morse Code encoder/decoder
Author: Parikshit Sonwane
Author-email: parik.sonwane06@gmail.com
Requires-Python: >=3.6
License-File: License
Dynamic: author
Dynamic: author-email
Dynamic: description
Dynamic: description-content-type
Dynamic: license-file
Dynamic: requires-python
Dynamic: summary
